{
    "id": 122615742,
    "name": "Glittering",
    "author": "Fleshy",
    "creators": ["Fleshy"],
    "verifier": "Fleshy",
    "verification": "https://youtu.be/Okhp8aSqd-k?is=12SsToI3NUIauthV",
    "percentToQualify": 100,
    "password": "Not Copyable",
    "records": [
        {
            "user": "BigPapi365",
            "link": "https://medal.tv/games/geometry-dash/clips/mnhExrC7jC0Wo1rEE?invite=cr-MSxicmUsMTk1MTk1ODA3",
            "percent": 100,
            "hz": 360
        },
    ]
}
