{
    "id": 135777053,
    "name": "Maple Treeway",
    "author": "Screendoe",
    "creators": ["Screendoe"],
    "verifier": "Screendoe",
    "verification": "https://youtu.be/JxjD6ojKWhU",
    "percentToQualify": 100,
    "password": "Not Copyable",
    "records": [   
        {
            "user": "Squidkid72",
            "link": "https://medal.tv/games/geometry-dash/clips/mjJlPv06zvgh5zteH?invite=cr-MSxRRTIsMjAxNjg2NTgw&v=14",
            "percent": 100,
            "hz": 240
        },   
        {
            "user": "YourLighy",
            "link": "https://medal.tv/games/geometry-dash/clips/mjJlPv06zvgh5zteH?invite=cr-MSxRRTIsMjAxNjg2NTgw&v=14",
            "percent": 100,
            "hz": 280
        },   
        {
            "user": "Fleshy",
            "link": "https://medal.tv/games/geometry-dash/clips/mnoHJG4ojRH6HRJHb?invite=cr-MSxnM3YsMjU2NzE5NzYx&v=300",
            "percent": 100,
            "hz": 240
        },   
        {
            "user": "Codedguy",
            "link": "https://medal.tv/games/geometry-dash/clips/mreSi1sHHwvHdXGXu?invite=cr-MSxIaUosMjE5MTU1NjY3&v=10",
            "percent": 100,
            "hz": 240
        },   
        {
            "user": "semeboy58",
            "link": "https://medal.tv/games/geometry-dash/clips/mrC1b2UB3isOmnUJC?invite=cr-MSxiU3ksMjUyNjkwMTg1",
            "percent": 100,
            "hz": 144
        },
        {
            "user": "Reaction",
            "link": "https://www.youtube.com/watch?v=_N31qGBmsLs",
            "percent": 100,
            "hz": 480
        }
    ]
}
